setup.py
client/__init__.py
client/client.py
client/client/__init__.py
client/client/add_contact.py
client/client/database_client.py
client/client/delete_contact.py
client/client/main_window.py
client/client/main_window_conv.py
client/client/start_dialog.py
client/client/transit.py
client/common/__init__.py
client/common/decor.py
client/common/descrpts.py
client/common/errors.py
client/common/metaclss.py
client/common/utils.py
client/common/variables.py
client/doc/__init__.py
client/doc/source/__init__.py
client/doc/source/conf.py
client/logs/__init__.py
client/logs/config_client_log.py
client/logs/config_server_log.py
client/project_unittests/__init__.py
client/project_unittests/test_client.py
client/project_unittests/test_server.py
messenger_client_project.egg-info/PKG-INFO
messenger_client_project.egg-info/SOURCES.txt
messenger_client_project.egg-info/dependency_links.txt
messenger_client_project.egg-info/requires.txt
messenger_client_project.egg-info/top_level.txt