Metadata-Version: 1.0
Name: messenger-client-project
Version: 0.0.2
Summary: messenger_client_project
Home-page: UNKNOWN
Author: Andrei Karachenko
Author-email: andrey141294@yandex.ru
License: UNKNOWN
Platform: UNKNOWN
